Metadata-Version: 1.0
Name: deepNeuralNet
Version: 0.0.2
Summary: various neural network algorithms
Home-page: UNKNOWN
Author: PINAKI SEN
Author-email: pinakisen.eenita@gmail.com
License: UNKNOWN
Platform: UNKNOWN
